miose_toolkit_llm/__init__.py
miose_toolkit_llm/clients/__init__.py
miose_toolkit_llm/clients/base.py
miose_toolkit_llm/clients/chat_ollama.py
miose_toolkit_llm/clients/chat_openai.py
miose_toolkit_llm/components/__init__.py
miose_toolkit_llm/components/base.py
miose_toolkit_llm/components/functions.py
miose_toolkit_llm/components/history.py
miose_toolkit_llm/components/json_resolver.py
miose_toolkit_llm/components/text.py
miose_toolkit_llm/components/vec_history.py
miose_toolkit_llm/creators/__init__.py
miose_toolkit_llm/creators/base.py
miose_toolkit_llm/creators/openai.py
miose_toolkit_llm/exceptions.py
miose_toolkit_llm/scene.py
miose_toolkit_llm/store.py
miose_toolkit_llm/tools/tokenizers/__init__.py
miose_toolkit_llm/tools/tokenizers/base.py
miose_toolkit_llm/tools/tokenizers/tiktoken.py
miose_toolkit_llm/tools/vector_dbs/__init__.py
miose_toolkit_llm/tools/vector_dbs/base.py
miose_toolkit_llm/tools/vector_dbs/choma.py
miose_toolkit_llm/tools/vector_dbs/qdrant.py
miose_toolkit_llm/utils.py
miose_toolkit_llm-0.0.2.dist-info/METADATA
miose_toolkit_llm-0.0.2.dist-info/WHEEL
miose_toolkit_llm-0.0.2.dist-info/entry_points.txt
miose_toolkit_llm-0.0.2.dist-info/RECORD
