Metadata-Version: 2.1
Name: miose-toolkit-llm
Version: 0.0.2
Summary: Miose Toolkit 大语言模型模块
Author: KroMiose
Author-email: li_xiangff@163.com
Requires-Python: >=3.8,<3.12
Classifier: Programming Language :: Python :: 3
Classifier: Programming Language :: Python :: 3.8
Classifier: Programming Language :: Python :: 3.9
Classifier: Programming Language :: Python :: 3.10
Classifier: Programming Language :: Python :: 3.11
Provides-Extra: all
Provides-Extra: openai
Provides-Extra: tiktoken
Requires-Dist: openai (>=0.27.0,<2.0.0) ; extra == "openai" or extra == "all"
Requires-Dist: tiktoken (>=0.6.0,<1.0.0) ; extra == "tiktoken" or extra == "all"
